tabpfn_extensions/__init__.py
tabpfn_extensions/test_utils.py
tabpfn_extensions/utils.py
tabpfn_extensions/benchmarking/__init__.py
tabpfn_extensions/benchmarking/experiment.py
tabpfn_extensions/embedding/__init__.py
tabpfn_extensions/embedding/tabpfn_embedding.py
tabpfn_extensions/hpo/__init__.py
tabpfn_extensions/hpo/search_space.py
tabpfn_extensions/hpo/tuned_tabpfn.py
tabpfn_extensions/interpretability/__init__.py
tabpfn_extensions/interpretability/experiments.py
tabpfn_extensions/interpretability/feature_selection.py
tabpfn_extensions/interpretability/pdp.py
tabpfn_extensions/interpretability/shap.py
tabpfn_extensions/interpretability/shapiq.py
tabpfn_extensions/many_class/__init__.py
tabpfn_extensions/many_class/_strategies.py
tabpfn_extensions/many_class/_utils.py
tabpfn_extensions/many_class/many_class_classifier.py
tabpfn_extensions/misc/__init__.py
tabpfn_extensions/misc/sklearn_compat.py
tabpfn_extensions/post_hoc_ensembles/__init__.py
tabpfn_extensions/post_hoc_ensembles/sklearn_interface.py
tabpfn_extensions/post_hoc_ensembles/utils.py
tabpfn_extensions/rf_pfn/__init__.py
tabpfn_extensions/rf_pfn/configs.py
tabpfn_extensions/rf_pfn/sklearn_based_decision_tree_tabpfn.py
tabpfn_extensions/rf_pfn/sklearn_based_random_forest_tabpfn.py
tabpfn_extensions/rf_pfn/utils.py
tabpfn_extensions/scoring/__init__.py
tabpfn_extensions/scoring/scoring_utils.py
tabpfn_extensions/sklearn_ensembles/__init__.py
tabpfn_extensions/sklearn_ensembles/configs.py
tabpfn_extensions/sklearn_ensembles/meta_models.py
tabpfn_extensions/sklearn_ensembles/weighted_ensemble.py
tabpfn_extensions/tabebm/__init__.py
tabpfn_extensions/tabebm/tabebm.py
tabpfn_extensions/unsupervised/__init__.py
tabpfn_extensions/unsupervised/experiments.py
tabpfn_extensions/unsupervised/unsupervised.py
tabpfn_extensions-0.2.1.dist-info/licenses/LICENSE
tabpfn_extensions-0.2.1.dist-info/METADATA
tabpfn_extensions-0.2.1.dist-info/WHEEL
tabpfn_extensions-0.2.1.dist-info/top_level.txt
tabpfn_extensions-0.2.1.dist-info/RECORD
