Metadata-Version: 2.4
Name: tabpfn-extensions
Version: 0.2.1
Summary: TabPFN: Foundation model for tabular data
Author: Leo Grinsztajn, Lennart Purucker, Arjun Krishnakumar, Max Körfer, Shi Bin Hoo, Robin Tibor Schirrmeister, Eddie Bergman, Klemens Flöge, Oscar Key, Dominik Safaric
Author-email: Noah Hollmann <noah.hollmann@charite.de>, Samuel Müller <muellesa@cs.uni-freiburg.de>, Frank Hutter <fh@cs.uni-freiburg.de>
License: 
Project-URL: documentation, https://priorlabs.ai/docs
Project-URL: source, https://github.com/PriorLabs/tabpfn-extensions
Classifier: Intended Audience :: Science/Research
Classifier: Intended Audience :: Developers
Classifier: License :: OSI Approved :: Apache Software License
Classifier: Programming Language :: Python
Classifier: Topic :: Software Development
Classifier: Topic :: Scientific/Engineering
Classifier: Operating System :: POSIX
Classifier: Operating System :: Unix
Classifier: Operating System :: MacOS
Classifier: Programming Language :: Python :: 3
Classifier: Programming Language :: Python :: 3.9
Classifier: Programming Language :: Python :: 3.10
Classifier: Programming Language :: Python :: 3.11
Classifier: Programming Language :: Python :: 3.12
Classifier: Programming Language :: Python :: 3.13
Requires-Python: >=3.9
License-File: LICENSE
Requires-Dist: torch<3,>=2.1
Requires-Dist: pandas<3,>=1.4.0
Requires-Dist: scikit-learn<1.7,>=1.6.0
Requires-Dist: scipy<2,>=1.11.1
Requires-Dist: tabpfn<7,>=6.0.5
Requires-Dist: tabpfn-common-utils[telemetry-interactive]>=0.2.0
Provides-Extra: interpretability
Requires-Dist: shap>=0.41.0; extra == "interpretability"
Requires-Dist: shapiq>=0.4.0; extra == "interpretability"
Requires-Dist: seaborn>=0.12.2; extra == "interpretability"
Provides-Extra: post-hoc-ensembles
Requires-Dist: llvmlite; extra == "post-hoc-ensembles"
Requires-Dist: hyperopt>=0.2.7; extra == "post-hoc-ensembles"
Requires-Dist: autogluon.tabular==1.4.0; extra == "post-hoc-ensembles"
Provides-Extra: hpo
Requires-Dist: hyperopt>=0.2.7; extra == "hpo"
Requires-Dist: setuptools>=67.0.0; extra == "hpo"
Provides-Extra: many-class
Provides-Extra: classifier-as-regressor
Provides-Extra: rf-pfn
Provides-Extra: unsupervised
Provides-Extra: all
Requires-Dist: shap>=0.41.0; extra == "all"
Requires-Dist: shapiq>=0.4.0; extra == "all"
Requires-Dist: seaborn>=0.12.2; extra == "all"
Requires-Dist: llvmlite>=0.30.0; extra == "all"
Requires-Dist: hyperopt>=0.2.7; extra == "all"
Requires-Dist: setuptools>=67.0.0; extra == "all"
Requires-Dist: autogluon.tabular==1.4.0; extra == "all"
Provides-Extra: dev
Requires-Dist: pre-commit>=3.0.0; extra == "dev"
Requires-Dist: ruff==0.8.6; extra == "dev"
Requires-Dist: mypy>=1.0.0; extra == "dev"
Requires-Dist: pytest>=8.0.0; extra == "dev"
Requires-Dist: pytest-xdist>=3.6.0; extra == "dev"
Requires-Dist: pytest-mock>=3.15.1; extra == "dev"
Dynamic: license-file
